pyndn/__init__.py
pyndn/control_parameters.py
pyndn/control_response.py
pyndn/data.py
pyndn/delegation_set.py
pyndn/digest_sha256_signature.py
pyndn/exclude.py
pyndn/face.py
pyndn/forwarding_flags.py
pyndn/generic_signature.py
pyndn/hmac_with_sha256_signature.py
pyndn/interest.py
pyndn/interest_filter.py
pyndn/key_locator.py
pyndn/link.py
pyndn/meta_info.py
pyndn/name.py
pyndn/network_nack.py
pyndn/node.py
pyndn/registration_options.py
pyndn/sha256_with_ecdsa_signature.py
pyndn/sha256_with_rsa_signature.py
pyndn/signature.py
pyndn/threadsafe_face.py
pyndn/validity_period.py
pyndn/contrib/__init__.py
pyndn/contrib/cocoapy/__init__.py
pyndn/contrib/cocoapy/cocoalibs.py
pyndn/contrib/cocoapy/cocoatypes.py
pyndn/contrib/cocoapy/runtime.py
pyndn/encoding/__init__.py
pyndn/encoding/element_reader.py
pyndn/encoding/oid.py
pyndn/encoding/protobuf_tlv.py
pyndn/encoding/tlv_0_1_1_wire_format.py
pyndn/encoding/tlv_0_1_wire_format.py
pyndn/encoding/tlv_0_2_wire_format.py
pyndn/encoding/tlv_0_3_wire_format.py
pyndn/encoding/tlv_wire_format.py
pyndn/encoding/wire_format.py
pyndn/encoding/der/__init__.py
pyndn/encoding/der/der.py
pyndn/encoding/der/der_exceptions.py
pyndn/encoding/der/der_node.py
pyndn/encoding/tlv/__init__.py
pyndn/encoding/tlv/tlv.py
pyndn/encoding/tlv/tlv_decoder.py
pyndn/encoding/tlv/tlv_encoder.py
pyndn/encoding/tlv/tlv_structure_decoder.py
pyndn/encrypt/__init__.py
pyndn/encrypt/access_manager_v2.py
pyndn/encrypt/consumer.py
pyndn/encrypt/consumer_db.py
pyndn/encrypt/decrypt_key.py
pyndn/encrypt/decryptor_v2.py
pyndn/encrypt/encrypt_error.py
pyndn/encrypt/encrypt_key.py
pyndn/encrypt/encrypted_content.py
pyndn/encrypt/encryptor_v2.py
pyndn/encrypt/group_manager.py
pyndn/encrypt/group_manager_db.py
pyndn/encrypt/interval.py
pyndn/encrypt/producer.py
pyndn/encrypt/producer_db.py
pyndn/encrypt/repetitive_interval.py
pyndn/encrypt/schedule.py
pyndn/encrypt/sqlite3_consumer_db.py
pyndn/encrypt/sqlite3_group_manager_db.py
pyndn/encrypt/sqlite3_producer_db.py
PyNDN-2.13b1.dist-info/COPYING
PyNDN-2.13b1.dist-info/METADATA
PyNDN-2.13b1.dist-info/WHEEL
PyNDN-2.13b1.dist-info/top_level.txt
PyNDN-2.13b1.dist-info/RECORD
