Metadata-Version: 2.1
Name: PyNDN
Version: 2.13b1
Summary: An NDN client library with TLV wire format support in native Python
Home-page: https://github.com/named-data/PyNDN2
Maintainer: Jeff Thompson
Maintainer-email: jefft0@remap.ucla.edu
License: LGPLv3
Keywords: NDN
Platform: UNKNOWN
Classifier: Development Status :: 4 - Beta
Classifier: Intended Audience :: Developers
Classifier: License :: OSI Approved :: GNU Lesser General Public License v3 or later (LGPLv3+)
Classifier: Programming Language :: Python :: 2
Classifier: Programming Language :: Python :: 2.7
Classifier: Programming Language :: Python :: 3
Classifier: Programming Language :: Python :: 3.4
Classifier: Programming Language :: Python :: 3.5
Classifier: Programming Language :: Python :: 3.6
Classifier: Programming Language :: Python :: 3.7
Classifier: Programming Language :: Python :: 3.8
Classifier: Programming Language :: Python :: Implementation :: CPython
Classifier: Programming Language :: Python :: Implementation :: PyPy
Classifier: Topic :: Software Development :: Libraries
Requires-Python: >=2.7, !=3.0.*, !=3.1.*, !=3.2.*, !=3.3.*
Requires-Dist: cryptography (~=2.3)
Requires-Dist: mmh3 (~=2.5)
Requires-Dist: protobuf (~=3.5)
Requires-Dist: trollius ; python_version == "2.7"
Provides-Extra: doc
Requires-Dist: sphinx (~=1.6.3) ; extra == 'doc'
Provides-Extra: test
Requires-Dist: pytest ; extra == 'test'
Requires-Dist: mock ; (python_version == "2.7") and extra == 'test'
